[
  {
    "authors": "Armel Soubeiga, Jessem Ettaghouti, Violaine Antoine, Alice Corteval, Nicolas Kerckhove, Sylvain Moreno",
    "type": "POSTER",
    "description": "Clustering de séries chronologiques de patients souffrant de douleurs chroniques",
    "annee": "2023",
    "lien": "https://hal.science/hal-04063254"
  },
  {
    "authors": "Armel Soubeiga, Jessem Ettaghouti, Violaine Antoine, Alice Corteval, Nicolas Kerckhove, Sylvain Moreno",
    "type": "Extraction et Gestion des Connaissances (EGC)",
    "description": "Clustering de séries chronologiques de patients souffrant de douleurs chroniques",
    "annee": "2023",
    "lien": "https://hal.science/hal-04063246"
  }
]
